Multiplexer/mux.v
module Mux_2x1 (
    input a, b, sl_1,
    output y
);
    assign y = sl_1 ? b : a;

endmodule

module Mux_4x1 (
    input a, b, c, d, sl_1, sl_0,
    output y
);
    wire y_1, y_2;

    Mux_2x1 mux_1 (a, b, sl_0, y_1);
    Mux_2x1 mux_2 (c, d, sl_0, y_2);

    Mux_2x1 mux_3 (y_1, y_2, sl_1, y);

endmodule

module Mux_8x1 (
    input a, b, c, d, e, f, g, h, sl_2, sl_1, sl_0,
    output y
);
    wire y_1, y_2;

    Mux_4x1 mux_1 (a, b, c, d, sl_1, sl_0, y_1);
    Mux_4x1 mux_2 (e, f, g, h, sl_1, sl_0, y_2);

    Mux_2x1 mux_3 (y_1, y_2, sl_2, y);

endmodule

Multiplexer/Testbench_Mux_2x1.v
module Testbench_2x1;
    reg a, b, sl_1;
    wire y;

    Mux_2x1 uud (
        .a(a),
        .b(b),
        .sl_1(sl_1),
        .y(y)
    );

    initial begin
        $monitor(
            "Time: %0t | a=%b | b=%b | sl_1=%b | sum=%b",
            $time,
            a, b, sl_1,
            y
        );

        $dumpfile("./op/Mux_2x1.vcd");
        $dumpvars(0, Testbench_2x1);

        for (integer i = 0; i < 2; i = i + 1) begin
            for (integer j = 0; j < 2; j = j + 1) begin
                for (integer k = 0; k < 2; k = k + 1) begin
                    sl_1 = i; a = j; b = k; #10;
                end
            end
        end
    end

endmodule

Multiplexer/op/Mux_2x1.vcd
$date
	Sat Mar 15 14:41:59 2025
$end
$version
	Icarus Verilog
$end
$timescale
	1s
$end
$scope module Testbench_2x1 $end
$var wire 1 ! y $end
$var reg 1 " a $end
$var reg 1 # b $end
$var reg 1 $ sl_1 $end
$scope module uud $end
$var wire 1 " a $end
$var wire 1 # b $end
$var wire 1 $ sl_1 $end
$var wire 1 ! y $end
$upscope $end
$scope begin $ivl_for_loop0 $end
$var integer 32 % i [31:0] $end
$scope begin $ivl_for_loop1 $end
$var integer 32 & j [31:0] $end
$scope begin $ivl_for_loop2 $end
$var integer 32 ' k [31:0] $end
$upscope $end
$upscope $end
$upscope $end
$upscope $end
$enddefinitions $end
$comment Show the parameter values. $end
$dumpall
$end
#0
$dumpvars
b0 '
b0 &
b0 %
0$
0#
0"
0!
$end
#10
1#
b1 '
#20
1!
0#
1"
b1 &
b0 '
#30
1#
b1 '
#40
0!
0#
0"
1$
b1 %
b0 &
b0 '
#50
1!
1#
b1 '
#60
0!
0#
1"
b1 &
b0 '
#70
1!
1#
b1 '
#80
b10 %
b10 &
b10 '
