AdderCircuits/adder.v
module HA (
    input a, b,
    output sum, carry
);
    assign sum = a ^ b;
    assign carry = a & b;

endmodule

module FAwithHA (
    input a, b, carry_in,
    output sum, carry_out
);
    wire s1, c1, c2;
    HA U1 (
        .a(a), .b(b),
        .sum(s1), .carry(c1)
    );

    HA U2 (
        .a(carry_in), .b(s1),
        .sum(sum), .carry(c2)
    );

    assign carry_out = c1 | c2;

endmodule

module FA (
    input a, b, carry_in,
    output sum, carry_out
);
    assign sum = (a ^ b) ^ carry_in;
    assign carry_out = (a & b) | (b & carry_in) | (a & carry_in);

endmodule

AdderCircuits/testbench_HA_FA.v
module TestBench_HA_FA;
    reg a, b, c_in;
    wire s, c_out;

    FAwithHA uud (
        .a(a), .b(b), .carry_in(c_in),
        .sum(s), .carry_out(c_out)
    );

    initial begin
        $monitor(
            "Time: %0t | a=%b | b=%b | c_in=%b | sum=%b | carry=%b",
            $time,
            a, b, c_in,
            s, c_out
        );

        $dumpfile("./op/FullAdderwithHalfAdder.vcd");
        $dumpvars(0, TestBench_HA_FA);

        a = 0; b = 0; c_in = 0; #10;
        a = 0; b = 0; c_in = 1; #10;
        a = 0; b = 1; c_in = 0; #10;
        a = 0; b = 1; c_in = 1; #10;
        a = 1; b = 0; c_in = 0; #10;
        a = 1; b = 0; c_in = 1; #10;
        a = 1; b = 1; c_in = 0; #10;
        a = 1; b = 1; c_in = 1; #10;
    end

endmodule

AdderCircuits/op/FullAdderwithHalfAdder.vcd
$date
	Sat Mar 15 17:47:11 2025
$end
$version
	Icarus Verilog
$end
$timescale
	1s
$end
$scope module TestBench_HA_FA $end
$var wire 1 ! s $end
$var wire 1 " c_out $end
$var reg 1 # a $end
$var reg 1 $ b $end
$var reg 1 % c_in $end
$scope module uud $end
$var wire 1 # a $end
$var wire 1 $ b $end
$var wire 1 % carry_in $end
$var wire 1 " carry_out $end
$var wire 1 ! sum $end
$var wire 1 & s1 $end
$var wire 1 ' c2 $end
$var wire 1 ( c1 $end
$scope module U1 $end
$var wire 1 # a $end
$var wire 1 $ b $end
$var wire 1 ( carry $end
$var wire 1 & sum $end
$upscope $end
$scope module U2 $end
$var wire 1 % a $end
$var wire 1 & b $end
$var wire 1 ' carry $end
$var wire 1 ! sum $end
$upscope $end
$upscope $end
$upscope $end
$enddefinitions $end
$comment Show the parameter values. $end
$dumpall
$end
#0
$dumpvars
0(
0'
0&
0%
0$
0#
0"
0!
$end
#10
1!
1%
#20
1&
0%
1$
#30
1"
0!
1'
1%
#40
0"
1!
0'
0%
0$
1#
#50
1"
0!
1'
1%
#60
0'
0&
1(
0%
1$
#70
1!
1%
