SubtractorCircuits/subtractor.v
module HS (
    input a, b,
    output difference, borrow
);
    assign difference = a ^ b;
    assign borrow = !a & b;

endmodule

module FSwithHS (
    input a, b, b_in,
    output diff, b_out
);
    wire d1, b1, b2;
    HS U1 (
        .a(a), .b(b),
        .difference(d1), .borrow(b1)
    );

    HS U2 (
        .a(b_in), .b(d1),
        .difference(diff), .borrow(b2)
    );

    assign b_out = b1 | b2;

endmodule

module FS (
    input a, b, b_in,
    output diff, b_out
);
    assign diff = a ^ b ^ b_in;
    assign b_out = (!a & b_in) + (!a & b) + (b & b_in);

endmodule

SubtractorCircuits/testbench_FS.v
module TestBench_FS;
    reg a, b, b_in;
    wire diff, b_out;

    FS uud (
        .a(a),
        .b(b),
        .b_in(b_in),
        .diff(diff),
        .b_out(b_out)
    );

    initial begin
        $monitor(
            "Time: %0t | a=%b | b=%b | borrow_in=%b | difference=%b | borrow_op=%b",
            $time,
            a, b, b_in,
            diff, b_out
        );

        $dumpfile("./op/FullSubtractor.vcd");
        $dumpvars(0, TestBench_FS);

        a = 0; b = 0; b_in = 0; #10;
        a = 0; b = 0; b_in = 1; #10;
        a = 0; b = 1; b_in = 0; #10;
        a = 0; b = 1; b_in = 1; #10;
        a = 1; b = 0; b_in = 0; #10;
        a = 1; b = 0; b_in = 1; #10;
        a = 1; b = 1; b_in = 0; #10;
        a = 1; b = 1; b_in = 1; #10;
    end

endmodule

SubtractorCircuits/op/FullSubtractor.vcd
$date
	Wed Mar 12 15:10:24 2025
$end
$version
	Icarus Verilog
$end
$timescale
	1s
$end
$scope module TestBench_FS $end
$var wire 1 ! diff $end
$var wire 1 " b_out $end
$var reg 1 # a $end
$var reg 1 $ b $end
$var reg 1 % b_in $end
$scope module uud $end
$var wire 1 # a $end
$var wire 1 $ b $end
$var wire 1 % b_in $end
$var wire 1 ! diff $end
$var wire 1 " b_out $end
$upscope $end
$upscope $end
$enddefinitions $end
$comment Show the parameter values. $end
$dumpall
$end
#0
$dumpvars
0%
0$
0#
0"
0!
$end
#10
1!
1"
1%
#20
1"
0%
1$
#30
0!
1"
1%
#40
1!
0"
0%
0$
1#
#50
0!
1%
#60
0%
1$
#70
1!
1"
1%
